_postgresql.pyd
pgserver/__init__.py
pgserver/_build.py
pgserver/_commands.py
pgserver/postgres_server.py
pgserver/py.typed
pgserver/utils.py
pgserver/pginstall/bin/clusterdb.exe
pgserver/pginstall/bin/createdb.exe
pgserver/pginstall/bin/createuser.exe
pgserver/pginstall/bin/dropdb.exe
pgserver/pginstall/bin/dropuser.exe
pgserver/pginstall/bin/ecpg.exe
pgserver/pginstall/bin/initdb.exe
pgserver/pginstall/bin/libecpg.dll
pgserver/pginstall/bin/libecpg_compat.dll
pgserver/pginstall/bin/libpgtypes.dll
pgserver/pginstall/bin/libpq.dll
pgserver/pginstall/bin/pg_amcheck.exe
pgserver/pginstall/bin/pg_archivecleanup.exe
pgserver/pginstall/bin/pg_basebackup.exe
pgserver/pginstall/bin/pg_checksums.exe
pgserver/pginstall/bin/pg_config.exe
pgserver/pginstall/bin/pg_controldata.exe
pgserver/pginstall/bin/pg_ctl.exe
pgserver/pginstall/bin/pg_dump.exe
pgserver/pginstall/bin/pg_dumpall.exe
pgserver/pginstall/bin/pg_isready.exe
pgserver/pginstall/bin/pg_receivewal.exe
pgserver/pginstall/bin/pg_recvlogical.exe
pgserver/pginstall/bin/pg_resetwal.exe
pgserver/pginstall/bin/pg_restore.exe
pgserver/pginstall/bin/pg_rewind.exe
pgserver/pginstall/bin/pg_test_fsync.exe
pgserver/pginstall/bin/pg_test_timing.exe
pgserver/pginstall/bin/pg_upgrade.exe
pgserver/pginstall/bin/pg_verifybackup.exe
pgserver/pginstall/bin/pg_waldump.exe
pgserver/pginstall/bin/pgbench.exe
pgserver/pginstall/bin/postgres.exe
pgserver/pginstall/bin/psql.exe
pgserver/pginstall/bin/reindexdb.exe
pgserver/pginstall/bin/vacuumdb.exe
pgserver/pginstall/include/ecpg_config.h
pgserver/pginstall/include/ecpg_informix.h
pgserver/pginstall/include/ecpgerrno.h
pgserver/pginstall/include/ecpglib.h
pgserver/pginstall/include/ecpgtype.h
pgserver/pginstall/include/libpq-events.h
pgserver/pginstall/include/libpq-fe.h
pgserver/pginstall/include/pg_config.h
pgserver/pginstall/include/pg_config_ext.h
pgserver/pginstall/include/pg_config_manual.h
pgserver/pginstall/include/pg_config_os.h
pgserver/pginstall/include/pgtypes.h
pgserver-0.1.4.dist-info/LICENSE
pgserver-0.1.4.dist-info/METADATA
pgserver-0.1.4.dist-info/WHEEL
pgserver-0.1.4.dist-info/top_level.txt
pgserver-0.1.4.dist-info/RECORD
